common/__init__.py
common/apps.py
common/consumer.py
common/errors.py
common/mixins.py
common/models.py
common/producer.py
common/utils.py
ticketo_common-0.1.22.dist-info/METADATA
ticketo_common-0.1.22.dist-info/WHEEL
ticketo_common-0.1.22.dist-info/top_level.txt
ticketo_common-0.1.22.dist-info/RECORD
